csession/__init__.py
csession/customsession.py
csession-0.1.4.dist-info/LICENSE
csession-0.1.4.dist-info/METADATA
csession-0.1.4.dist-info/WHEEL
csession-0.1.4.dist-info/top_level.txt
csession-0.1.4.dist-info/RECORD
