Metadata-Version: 2.1
Name: csession
Version: 0.1.4
Summary: Create a custom Session wrapped around the requests.Session
Home-page: https://github.com/ManuelZierl/csession
Author: Manuel Zierl
Author-email: manuel.zierl@web.de
License: UNKNOWN
Project-URL: Bug Tracker, https://github.com/ManuelZierl/csession/issues
Platform: UNKNOWN
Classifier: Programming Language :: Python :: 3
Classifier: License :: OSI Approved :: MIT License
Classifier: Operating System :: OS Independent
Requires-Python: >=3.6
License-File: LICENSE
